inspecta/__init__.py
inspecta/__init__.pyc
inspecta/inspector.py
inspecta/inspector.pyc
inspecta/tests/__init__.py
inspecta/tests/__main__.py
inspecta/tests/helper.py
inspecta/tests/test_inspector.py
inspecta-0.1.3.dist-info/METADATA
inspecta-0.1.3.dist-info/WHEEL
inspecta-0.1.3.dist-info/top_level.txt
inspecta-0.1.3.dist-info/zip-safe
inspecta-0.1.3.dist-info/RECORD
