Metadata-Version: 2.1
Name: inspecta
Version: 0.1.3
Summary: A colorized object pretty printer - for Python.
Home-page: https://github.com/grimen/python-inspecta
Author: Jonas Grimfelt
Author-email: grimen@gmail.com
License: MIT
Download-URL: https://github.com/grimen/python-inspecta
Project-URL: repository, https://github.com/grimen/python-inspecta
Project-URL: bugs, https://github.com/grimen/python-inspecta/issues
Keywords: inspector,inspection,color,colors,syntax-highlighting,prettyprinter,pretty-printer,debugging,terminal
Platform: UNKNOWN
Classifier: Topic :: Software Development :: Libraries
Classifier: Development Status :: 5 - Production/Stable
Classifier: Intended Audience :: Developers
Classifier: License :: OSI Approved :: MIT License
Classifier: Operating System :: POSIX
Classifier: Programming Language :: Python
Classifier: Programming Language :: Python :: 2
Classifier: Programming Language :: Python :: 3
Classifier: Programming Language :: Python :: Implementation :: CPython
Classifier: Programming Language :: Python :: Implementation :: PyPy
